jarvis_arp/__init__.py
jarvis_arp-0.1.0a5.dist-info/licenses/LICENSE
jarvis_arp-0.1.0a5.dist-info/METADATA
jarvis_arp-0.1.0a5.dist-info/WHEEL
jarvis_arp-0.1.0a5.dist-info/top_level.txt
jarvis_arp-0.1.0a5.dist-info/RECORD
