Metadata-Version: 2.4
Name: jarvis-arp
Version: 0.1.0a5
Summary: Meta-package that installs the full JARVIS ARP stack (runtime, model, tool registry).
Author: Agent Runtime Protocol
License: MIT License
Project-URL: Repository, https://github.com/AgentRuntimeProtocol/Arp_Release
Project-URL: Issues, https://github.com/AgentRuntimeProtocol/Arp_Release/issues
Requires-Python: >=3.10
License-File: LICENSE
Requires-Dist: jarvis-runtime==0.1.0a5
Requires-Dist: jarvis-model==0.1.0a5
Requires-Dist: jarvis-tool-registry==0.1.0a5
Dynamic: license-file
